Workbook

Sheet Assumptions
A1: CONDO REAL ESTATE INVESTMENT MODEL
A3: INPUT PARAMETERS | B3: Value | C3: Unit | D3: Description | F3: SOURCES OF FUNDS | G3: Amount ($) | H3: % of Total
A4: Purchase Price | B4: 480000 | C4: USD | D4: Agreed purchase contract price | F4: Senior Mortgage Loan | G4: =$B$4*$B$7 -> 360000 | H4: =G4/$G$7 -> 0.67475166
A5: Closing Costs | B5: =0.025*B4 -> 12000 | C5: USD | D5: Escrow, title, legal & transfer tax (~2.0%) | F5: Seller Concessions | G5: =$B$20 -> 30000 | H5: =G5/$G$7 -> 0.056229305
A6: Initial Renovation & Setup | B6: 0 | C6: USD | D6: Immediate unit repairs & capital setup | F6: Investor Equity (Cash Required) | G6: =G15-G4-G5 -> 143529.63 | H6: =G6/$G$7 -> 0.26901904
A7: Loan-to-Value (LTV) | B7: 0.75 | C7: % | D7: Senior mortgage debt financing ratio | F7: Total Sources | G7: =SUM(G4:G6) -> 533529.63 | H7: =SUM(H4:H6) -> 1
A8: Annual Mortgage Interest Rate | B8: 0.0725 | C8: % | D8: Fixed annual mortgage loan interest rate
A9: Loan Term (Years) | B9: 30 | C9: Years | D9: Mortgage amortization term | F9: USES OF FUNDS | G9: Amount ($) | H9: % of Total
A10: Gross Annual Rental Income | B10: 45000 | C10: USD / Yr | D10: Base market rent ($3,000 / month) | F10: Property Purchase Price | G10: =$B$4 -> 480000 | H10: =G10/$G$15 -> 0.89966888
A11: Vacancy & Credit Loss Rate | B11: 0.05 | C11: % | D11: Allowance for tenant turnover / vacancy | F11: Closing Costs & Fees | G11: =$B$5 -> 12000 | H11: =G11/$G$15 -> 0.022491722
A12: Annual HOA Dues | B12: =600*12 -> 7200 | C12: USD / Yr | D12: Condominium association dues ($400/mo) | F12: Initial Renovation & Setup | G12: =$B$6 -> 0 | H12: =G12/$G$15 -> 0
A13: Annual Property Taxes | B13: 4000 | C13: USD / Yr | D13: Local municipal property assessment (~1.2%) | F13: Rate Buydown | G13: =$B$19 -> 40000 | H13: =G13/$G$15 -> 0.074972407
A14: Annual Property Insurance | B14: 3000 | C14: USD / Yr | D14: Condo hazard & liability insurance policy | F14: Working Capital | G14: =-SUMIF('Cash Flows'!$C$27:$AF$27, "<0") -> 1529.6257 | H14: =G14/$G$15 -> 0.002866993
A15: Annual Rent & Expense Growth | B15: 0.03 | C15: % YoY | D15: Annual inflation & market growth rate | F15: Total Uses | G15: =SUM(G10:G14) -> 533529.63 | H15: =SUM(H10:H14) -> 1
A16: Target Exit Year | B16: 5 | C16: Year (1-30) | D16: Planned disposition year within 30-yr horizon | F16: Sources & Uses Balance Check | G16: =G7-G15 -> 0 | H16: =IF(G16=0, "BALANCED ✓", "OUT OF BALANCE ⚠️") -> BALANCED ✓
A17: Projected Exit Price | B17: 560000 | C17: USD | D17: Estimated gross disposition value at exit | F17: EXECUTIVE RETURN SUMMARY | G17: Value | H17: Metric Type / Description
A18: Cost of Sale Rate | B18: 0.03 | C18: % | D18: Broker commissions & closing legal at exit | F18: Holding Period | G18: =$B$16&" Years" -> 5 Years | H18: Target investment holding horizon
A19: Rate Buydown | B19: 40000 | C19: USD | D19: Points or upfront fee to buy down interest rate | F19: Initial Equity Invested | G19: =G6 -> 143529.63 | H19: Total cash required at acquisition (t=0)
A20: Seller Concessions | B20: 30000 | C20: USD | D20: Seller credit contributed toward buyer closing costs | F20: Project Levered IRR | G20: {=IFERROR(IRR('Cash Flows'!$B$27:INDEX('Cash Flows'!$B$27:$AF$27, 1, $B$16+1)), "N/A")} -> 0.10208677 | H20: Annualized Internal Rate of Return
F21: Year 1 Cash-on-Cash Return | G21: =IFERROR('Cash Flows'!C27/G6, "N/A") -> -0.0083123107 | H21: First-year net cash yield on invested equity
F22: Total Net Cash Flow | G22: {=IFERROR(SUM('Cash Flows'!$B$27:INDEX('Cash Flows'!$B$27:$AF$27, 1, $B$16+1)), 0)} -> 90242.589 | H22: Cumulative net cash distributions over hold
A23: Rate Buydown (year) | B23: % | F23: Equity Multiple (MOIC) | G23: {=IFERROR(SUM('Cash Flows'!$C$27:INDEX('Cash Flows'!$C$27:$AF$27, 1, $B$16))/G6, 0)} -> 1.6287384 | H23: Total cash distributed divided by initial equity
A24: 1 | B24: 0.03 | F24: Projected Gross Exit Price | G24: =$B$17 -> 560000 | H24: Unlevered gross disposition value at exit
A25: =1+A24 -> 2 | B25: 0.02
A26: =1+A25 -> 3 | B26: 0.01 | F26: asset growth gross YoY | G26: =(B17/B4)^(1/B16)-1 -> 0.031310306
A27: =1+A26 -> 4 | B27: 0 | F27: per annum rate cost | G27: ='Cash Flows'!C30 -> -0.0024855476
A28: =1+A27 -> 5 | B28: 0 | F28: irr hold | G28: ='Cash Flows'!A33 -> 0.013820723
A30: Error Check | B30: =not(OR(AND(SUM(B24:B28)=0, B19=0), AND(SUM(B24:B28)>0, B19>0))) -> FALSE | F30: per annum carrying cost | G30: =sum(B12:B14)/B4 -> 0.029583333

Sheet Cash Flows
A1: 30-YEAR CONDO INVESTMENT CASH FLOW PRO-FORMA
A2: Period (t) | B2: 0 | C2: 1 | D2: 2 | E2: 3 | F2: 4 | G2: 5 | H2: 6 | I2: 7 | J2: 8 | K2: 9 | L2: 10 | M2: 11 | N2: 12 | O2: 13 | P2: 14 | Q2: 15 | R2: 16 | S2: 17 | T2: 18 | U2: 19 | V2: 20 | W2: 21 | X2: 22 | Y2: 23 | Z2: 24 | AA2: 25 | AB2: 26 | AC2: 27 | AD2: 28 | AE2: 29 | AF2: 30
A3: Investment Timeline | B3: Year 0 | C3: Year 1 | D3: Year 2 | E3: Year 3 | F3: Year 4 | G3: Year 5 | H3: Year 6 | I3: Year 7 | J3: Year 8 | K3: Year 9 | L3: Year 10 | M3: Year 11 | N3: Year 12 | O3: Year 13 | P3: Year 14 | Q3: Year 15 | R3: Year 16 | S3: Year 17 | T3: Year 18 | U3: Year 19 | V3: Year 20 | W3: Year 21 | X3: Year 22 | Y3: Year 23 | Z3: Year 24 | AA3: Year 25 | AB3: Year 26 | AC3: Year 27 | AD3: Year 28 | AE3: Year 29 | AF3: Year 30
A4: OPERATING CASH FLOW SCHEDULE (UNLEVERED)
A5: Gross Scheduled Rental Income | B5: 0 | C5: =IF(C$2<=Assumptions!$B$16, Assumptions!$B$10 * (1 + Assumptions!$B$15)^(C$2-1), 0) -> 45000 | D5: =IF(D$2<=Assumptions!$B$16, Assumptions!$B$10 * (1 + Assumptions!$B$15)^(D$2-1), 0) -> 46350 | E5: =IF(E$2<=Assumptions!$B$16, Assumptions!$B$10 * (1 + Assumptions!$B$15)^(E$2-1), 0) -> 47740.5 | F5: =IF(F$2<=Assumptions!$B$16, Assumptions!$B$10 * (1 + Assumptions!$B$15)^(F$2-1), 0) -> 49172.715 | G5: =IF(G$2<=Assumptions!$B$16, Assumptions!$B$10 * (1 + Assumptions!$B$15)^(G$2-1), 0) -> 50647.896 | H5: =IF(H$2<=Assumptions!$B$16, Assumptions!$B$10 * (1 + Assumptions!$B$15)^(H$2-1), 0) -> 0 | I5: =IF(I$2<=Assumptions!$B$16, Assumptions!$B$10 * (1 + Assumptions!$B$15)^(I$2-1), 0) -> 0 | J5: =IF(J$2<=Assumptions!$B$16, Assumptions!$B$10 * (1 + Assumptions!$B$15)^(J$2-1), 0) -> 0 | ... AF5: =IF(AF$2<=Assumptions!$B$16, Assumptions!$B$10 * (1 + Assumptions!$B$15)^(AF$2-1), 0) -> 0
A6: Vacancy & Credit Loss (-) | B6: 0 | C6: =-C5*Assumptions!$B$11 -> -2250 | D6: =-D5*Assumptions!$B$11 -> -2317.5 | E6: =-E5*Assumptions!$B$11 -> -2387.025 | F6: =-F5*Assumptions!$B$11 -> -2458.6357 | G6: =-G5*Assumptions!$B$11 -> -2532.3948 | H6: =-H5*Assumptions!$B$11 -> 0 | I6: =-I5*Assumptions!$B$11 -> 0 | J6: =-J5*Assumptions!$B$11 -> 0 | ... AF6: =-AF5*Assumptions!$B$11 -> 0
A7: Effective Gross Income (EGI) | B7: 0 | C7: =C5+C6 -> 42750 | D7: =D5+D6 -> 44032.5 | E7: =E5+E6 -> 45353.475 | F7: =F5+F6 -> 46714.079 | G7: =G5+G6 -> 48115.502 | H7: =H5+H6 -> 0 | I7: =I5+I6 -> 0 | J7: =J5+J6 -> 0 | ... AF7: =AF5+AF6 -> 0
A8: Condominium HOA Dues (-) | B8: 0 | C8: =IF(C$2<=Assumptions!$B$16, -Assumptions!$B$12 * (1 + Assumptions!$B$15)^(C$2-1), 0) -> -7200 | D8: =IF(D$2<=Assumptions!$B$16, -Assumptions!$B$12 * (1 + Assumptions!$B$15)^(D$2-1), 0) -> -7416 | E8: =IF(E$2<=Assumptions!$B$16, -Assumptions!$B$12 * (1 + Assumptions!$B$15)^(E$2-1), 0) -> -7638.48 | F8: =IF(F$2<=Assumptions!$B$16, -Assumptions!$B$12 * (1 + Assumptions!$B$15)^(F$2-1), 0) -> -7867.6344 | G8: =IF(G$2<=Assumptions!$B$16, -Assumptions!$B$12 * (1 + Assumptions!$B$15)^(G$2-1), 0) -> -8103.6634 | H8: =IF(H$2<=Assumptions!$B$16, -Assumptions!$B$12 * (1 + Assumptions!$B$15)^(H$2-1), 0) -> 0 | I8: =IF(I$2<=Assumptions!$B$16, -Assumptions!$B$12 * (1 + Assumptions!$B$15)^(I$2-1), 0) -> 0 | J8: =IF(J$2<=Assumptions!$B$16, -Assumptions!$B$12 * (1 + Assumptions!$B$15)^(J$2-1), 0) -> 0 | ... AF8: =IF(AF$2<=Assumptions!$B$16, -Assumptions!$B$12 * (1 + Assumptions!$B$15)^(AF$2-1), 0) -> 0
A9: Property Taxes (-) | B9: 0 | C9: =IF(C$2<=Assumptions!$B$16, -Assumptions!$B$13 * (1 + Assumptions!$B$15)^(C$2-1), 0) -> -4000 | D9: =IF(D$2<=Assumptions!$B$16, -Assumptions!$B$13 * (1 + Assumptions!$B$15)^(D$2-1), 0) -> -4120 | E9: =IF(E$2<=Assumptions!$B$16, -Assumptions!$B$13 * (1 + Assumptions!$B$15)^(E$2-1), 0) -> -4243.6 | F9: =IF(F$2<=Assumptions!$B$16, -Assumptions!$B$13 * (1 + Assumptions!$B$15)^(F$2-1), 0) -> -4370.908 | G9: =IF(G$2<=Assumptions!$B$16, -Assumptions!$B$13 * (1 + Assumptions!$B$15)^(G$2-1), 0) -> -4502.0352 | H9: =IF(H$2<=Assumptions!$B$16, -Assumptions!$B$13 * (1 + Assumptions!$B$15)^(H$2-1), 0) -> 0 | I9: =IF(I$2<=Assumptions!$B$16, -Assumptions!$B$13 * (1 + Assumptions!$B$15)^(I$2-1), 0) -> 0 | J9: =IF(J$2<=Assumptions!$B$16, -Assumptions!$B$13 * (1 + Assumptions!$B$15)^(J$2-1), 0) -> 0 | ... AF9: =IF(AF$2<=Assumptions!$B$16, -Assumptions!$B$13 * (1 + Assumptions!$B$15)^(AF$2-1), 0) -> 0
A10: Property Insurance (-) | B10: 0 | C10: =IF(C$2<=Assumptions!$B$16, -Assumptions!$B$14 * (1 + Assumptions!$B$15)^(C$2-1), 0) -> -3000 | D10: =IF(D$2<=Assumptions!$B$16, -Assumptions!$B$14 * (1 + Assumptions!$B$15)^(D$2-1), 0) -> -3090 | E10: =IF(E$2<=Assumptions!$B$16, -Assumptions!$B$14 * (1 + Assumptions!$B$15)^(E$2-1), 0) -> -3182.7 | F10: =IF(F$2<=Assumptions!$B$16, -Assumptions!$B$14 * (1 + Assumptions!$B$15)^(F$2-1), 0) -> -3278.181 | G10: =IF(G$2<=Assumptions!$B$16, -Assumptions!$B$14 * (1 + Assumptions!$B$15)^(G$2-1), 0) -> -3376.5264 | H10: =IF(H$2<=Assumptions!$B$16, -Assumptions!$B$14 * (1 + Assumptions!$B$15)^(H$2-1), 0) -> 0 | I10: =IF(I$2<=Assumptions!$B$16, -Assumptions!$B$14 * (1 + Assumptions!$B$15)^(I$2-1), 0) -> 0 | J10: =IF(J$2<=Assumptions!$B$16, -Assumptions!$B$14 * (1 + Assumptions!$B$15)^(J$2-1), 0) -> 0 | ... AF10: =IF(AF$2<=Assumptions!$B$16, -Assumptions!$B$14 * (1 + Assumptions!$B$15)^(AF$2-1), 0) -> 0
A11: Total Operating Expenses (-) | B11: 0 | C11: =SUM(C8:C10) -> -14200 | D11: =SUM(D8:D10) -> -14626 | E11: =SUM(E8:E10) -> -15064.78 | F11: =SUM(F8:F10) -> -15516.723 | G11: =SUM(G8:G10) -> -15982.225 | H11: =SUM(H8:H10) -> 0 | I11: =SUM(I8:I10) -> 0 | J11: =SUM(J8:J10) -> 0 | ... AF11: =SUM(AF8:AF10) -> 0
A12: Net Operating Income (NOI) | B12: 0 | C12: =C7+C11 -> 28550 | D12: =D7+D11 -> 29406.5 | E12: =E7+E11 -> 30288.695 | F12: =F7+F11 -> 31197.356 | G12: =G7+G11 -> 32133.277 | H12: =H7+H11 -> 0 | I12: =I7+I11 -> 0 | J12: =J7+J11 -> 0 | ... AF12: =AF7+AF11 -> 0
A14: DEBT SERVICE & LOAN SCHEDULE
A15: Beginning Loan Balance | B15: 0 | C15: =IF(C$2<=Assumptions!$B$16, B19, 0) -> 360000 | D15: =IF(D$2<=Assumptions!$B$16, C19, 0) -> 345556.94 | E15: =IF(E$2<=Assumptions!$B$16, D19, 0) -> 333955.61 | F15: =IF(F$2<=Assumptions!$B$16, E19, 0) -> 325084.78 | G15: =IF(G$2<=Assumptions!$B$16, F19, 0) -> 318910.36 | H15: =IF(H$2<=Assumptions!$B$16, G19, 0) -> 0 | I15: =IF(I$2<=Assumptions!$B$16, H19, 0) -> 0 | J15: =IF(J$2<=Assumptions!$B$16, I19, 0) -> 0 | ... AF15: =IF(AF$2<=Assumptions!$B$16, AE19, 0) -> 0
A16: Annual Debt Service (Total Payment) (-) | B16: 0 | C16: =IF(AND(C$2<=Assumptions!$B$16, C15>0), PMT(Assumptions!$B$8, Assumptions!$B$9, Assumptions!$G$4), 0) -> -29743.063 | D16: =IF(AND(D$2<=Assumptions!$B$16, D15>0), PMT(Assumptions!$B$8, Assumptions!$B$9, Assumptions!$G$4), 0) -> -29743.063 | E16: =IF(AND(E$2<=Assumptions!$B$16, E15>0), PMT(Assumptions!$B$8, Assumptions!$B$9, Assumptions!$G$4), 0) -> -29743.063 | F16: =IF(AND(F$2<=Assumptions!$B$16, F15>0), PMT(Assumptions!$B$8, Assumptions!$B$9, Assumptions!$G$4), 0) -> -29743.063 | G16: =IF(AND(G$2<=Assumptions!$B$16, G15>0), PMT(Assumptions!$B$8, Assumptions!$B$9, Assumptions!$G$4), 0) -> -29743.063 | H16: =IF(AND(H$2<=Assumptions!$B$16, H15>0), PMT(Assumptions!$B$8, Assumptions!$B$9, Assumptions!$G$4), 0) -> 0 | I16: =IF(AND(I$2<=Assumptions!$B$16, I15>0), PMT(Assumptions!$B$8, Assumptions!$B$9, Assumptions!$G$4), 0) -> 0 | J16: =IF(AND(J$2<=Assumptions!$B$16, J15>0), PMT(Assumptions!$B$8, Assumptions!$B$9, Assumptions!$G$4), 0) -> 0 | ... AF16: =IF(AND(AF$2<=Assumptions!$B$16, AF15>0), PMT(Assumptions!$B$8, Assumptions!$B$9, Assumptions!$G$4), 0) -> 0
A17: Interest Payment Portion (-) | B17: 0 | C17: =IF(C16<0, -C15*(Assumptions!$B$8-IFERROR(VLOOKUP(C$2, Assumptions!$A$24:$B$28, 2, FALSE), 0)), 0) -> -15300 | D17: =IF(D16<0, -D15*(Assumptions!$B$8-IFERROR(VLOOKUP(D$2, Assumptions!$A$24:$B$28, 2, FALSE), 0)), 0) -> -18141.739 | E17: =IF(E16<0, -E15*(Assumptions!$B$8-IFERROR(VLOOKUP(E$2, Assumptions!$A$24:$B$28, 2, FALSE), 0)), 0) -> -20872.226 | F17: =IF(F16<0, -F15*(Assumptions!$B$8-IFERROR(VLOOKUP(F$2, Assumptions!$A$24:$B$28, 2, FALSE), 0)), 0) -> -23568.646 | G17: =IF(G16<0, -G15*(Assumptions!$B$8-IFERROR(VLOOKUP(G$2, Assumptions!$A$24:$B$28, 2, FALSE), 0)), 0) -> -23121.001 | H17: =IF(H16<0, -H15*(Assumptions!$B$8-IFERROR(VLOOKUP(H$2, Assumptions!$A$24:$B$28, 2, FALSE), 0)), 0) -> 0 | I17: =IF(I16<0, -I15*(Assumptions!$B$8-IFERROR(VLOOKUP(I$2, Assumptions!$A$24:$B$28, 2, FALSE), 0)), 0) -> 0 | J17: =IF(J16<0, -J15*(Assumptions!$B$8-IFERROR(VLOOKUP(J$2, Assumptions!$A$24:$B$28, 2, FALSE), 0)), 0) -> 0 | ... AF17: =IF(AF16<0, -AF15*(Assumptions!$B$8-IFERROR(VLOOKUP(AF$2, Assumptions!$A$24:$B$28, 2, FALSE), 0)), 0) -> 0
A18: Principal Paydown Portion (-) | B18: 0 | C18: =IF(C16<0, C16-C17, 0) -> -14443.063 | D18: =IF(D16<0, D16-D17, 0) -> -11601.324 | E18: =IF(E16<0, E16-E17, 0) -> -8870.837 | F18: =IF(F16<0, F16-F17, 0) -> -6174.4165 | G18: =IF(G16<0, G16-G17, 0) -> -6622.0617 | H18: =IF(H16<0, H16-H17, 0) -> 0 | I18: =IF(I16<0, I16-I17, 0) -> 0 | J18: =IF(J16<0, J16-J17, 0) -> 0 | ... AF18: =IF(AF16<0, AF16-AF17, 0) -> 0
A19: Ending Loan Balance | B19: =Assumptions!$G$4 -> 360000 | C19: =IF(C$2<=Assumptions!$B$16, MAX(0, C15+C18), 0) -> 345556.94 | D19: =IF(D$2<=Assumptions!$B$16, MAX(0, D15+D18), 0) -> 333955.61 | E19: =IF(E$2<=Assumptions!$B$16, MAX(0, E15+E18), 0) -> 325084.78 | F19: =IF(F$2<=Assumptions!$B$16, MAX(0, F15+F18), 0) -> 318910.36 | G19: =IF(G$2<=Assumptions!$B$16, MAX(0, G15+G18), 0) -> 312288.3 | H19: =IF(H$2<=Assumptions!$B$16, MAX(0, H15+H18), 0) -> 0 | I19: =IF(I$2<=Assumptions!$B$16, MAX(0, I15+I18), 0) -> 0 | J19: =IF(J$2<=Assumptions!$B$16, MAX(0, J15+J18), 0) -> 0 | ... AF19: =IF(AF$2<=Assumptions!$B$16, MAX(0, AF15+AF18), 0) -> 0
A20: CAPITAL TRANSACTIONS & TERMINAL EXIT SCHEDULE
A21: Gross Exit Disposition Price | B21: 0 | C21: =IF(C$2=Assumptions!$B$16, Assumptions!$B$17, 0) -> 0 | D21: =IF(D$2=Assumptions!$B$16, Assumptions!$B$17, 0) -> 0 | E21: =IF(E$2=Assumptions!$B$16, Assumptions!$B$17, 0) -> 0 | F21: =IF(F$2=Assumptions!$B$16, Assumptions!$B$17, 0) -> 0 | G21: =IF(G$2=Assumptions!$B$16, Assumptions!$B$17, 0) -> 560000 | H21: =IF(H$2=Assumptions!$B$16, Assumptions!$B$17, 0) -> 0 | I21: =IF(I$2=Assumptions!$B$16, Assumptions!$B$17, 0) -> 0 | J21: =IF(J$2=Assumptions!$B$16, Assumptions!$B$17, 0) -> 0 | ... AF21: =IF(AF$2=Assumptions!$B$16, Assumptions!$B$17, 0) -> 0
A22: Cost of Sale (Brokerage & Legal) (-) | B22: 0 | C22: =IF(C21>0, -C21*Assumptions!$B$18, 0) -> 0 | D22: =IF(D21>0, -D21*Assumptions!$B$18, 0) -> 0 | E22: =IF(E21>0, -E21*Assumptions!$B$18, 0) -> 0 | F22: =IF(F21>0, -F21*Assumptions!$B$18, 0) -> 0 | G22: =IF(G21>0, -G21*Assumptions!$B$18, 0) -> -16800 | H22: =IF(H21>0, -H21*Assumptions!$B$18, 0) -> 0 | I22: =IF(I21>0, -I21*Assumptions!$B$18, 0) -> 0 | J22: =IF(J21>0, -J21*Assumptions!$B$18, 0) -> 0 | ... AF22: =IF(AF21>0, -AF21*Assumptions!$B$18, 0) -> 0
A23: Net Exit Disposition Proceeds | B23: 0 | C23: =C21+C22 -> 0 | D23: =D21+D22 -> 0 | E23: =E21+E22 -> 0 | F23: =F21+F22 -> 0 | G23: =G21+G22 -> 543200 | H23: =H21+H22 -> 0 | I23: =I21+I22 -> 0 | J23: =J21+J22 -> 0 | ... AF23: =AF21+AF22 -> 0
A24: Senior Mortgage Payoff at Exit (-) | B24: 0 | C24: =IF(C$2=Assumptions!$B$16, -C19, 0) -> 0 | D24: =IF(D$2=Assumptions!$B$16, -D19, 0) -> 0 | E24: =IF(E$2=Assumptions!$B$16, -E19, 0) -> 0 | F24: =IF(F$2=Assumptions!$B$16, -F19, 0) -> 0 | G24: =IF(G$2=Assumptions!$B$16, -G19, 0) -> -312288.3 | H24: =IF(H$2=Assumptions!$B$16, -H19, 0) -> 0 | I24: =IF(I$2=Assumptions!$B$16, -I19, 0) -> 0 | J24: =IF(J$2=Assumptions!$B$16, -J19, 0) -> 0 | ... AF24: =IF(AF$2=Assumptions!$B$16, -AF19, 0) -> 0
A25: Net Terminal Capital Proceeds | B25: 0 | C25: =C23+C24 -> 0 | D25: =D23+D24 -> 0 | E25: =E23+E24 -> 0 | F25: =F23+F24 -> 0 | G25: =G23+G24 -> 230911.7 | H25: =H23+H24 -> 0 | I25: =I23+I24 -> 0 | J25: =J23+J24 -> 0 | ... AF25: =AF23+AF24 -> 0
A27: NET LEVERED CASH FLOW | B27: =-Assumptions!$G$6 -> -143529.63 | C27: =IF(C$2<=Assumptions!$B$16, C12+C16+C25, 0) -> -1193.0628 | D27: =IF(D$2<=Assumptions!$B$16, D12+D16+D25, 0) -> -336.56284 | E27: =IF(E$2<=Assumptions!$B$16, E12+E16+E25, 0) -> 545.63216 | F27: =IF(F$2<=Assumptions!$B$16, F12+F16+F25, 0) -> 1454.293 | G27: =IF(G$2<=Assumptions!$B$16, G12+G16+G25, 0) -> 233301.92 | H27: =IF(H$2<=Assumptions!$B$16, H12+H16+H25, 0) -> 0 | I27: =IF(I$2<=Assumptions!$B$16, I12+I16+I25, 0) -> 0 | J27: =IF(J$2<=Assumptions!$B$16, J12+J16+J25, 0) -> 0 | ... AF27: =IF(AF$2<=Assumptions!$B$16, AF12+AF16+AF25, 0) -> 0
A28: Cumulative Net Cash Flow | B28: =B27 -> -143529.63 | C28: =B28+C27 -> -144722.69 | D28: =C28+D27 -> -145059.25 | E28: =D28+E27 -> -144513.62 | F28: =E28+F27 -> -143059.33 | G28: =F28+G27 -> 90242.589 | H28: =G28+H27 -> 90242.589 | I28: =H28+I27 -> 90242.589 | J28: =I28+J27 -> 90242.589 | ... AF28: =AE28+AF27 -> 90242.589
B30: rate cost | C30: =C27/Assumptions!B4 -> -0.0024855476
A32: irr hold | B32: =B27 -> -143529.63 | C32: =C27 -> -1193.0628 | D32: =D27 -> -336.56284 | E32: =E27 -> 545.63216 | F32: =F27 -> 1454.293 | G32: =G27-(Assumptions!B17-Assumptions!B4) -> 153301.92
A33: =irr(B32:G32) -> 0.013820723
